pfrpq/__init__.py
pfrpq/example.py
pfrpq/lib.py
pfrpq-0.0.1.dist-info/METADATA
pfrpq-0.0.1.dist-info/WHEEL
pfrpq-0.0.1.dist-info/licenses/LICENSE
pfrpq-0.0.1.dist-info/RECORD
