Metadata-Version: 2.1
Name: pfrpq
Version: 0.0.1
Summary: Perceptual Full-Reference Pairwise Quality Metric
Project-URL: Homepage, https://github.com/naugam/pfrpq
Project-URL: Bug Tracker, https://github.com/naugam/pfrpq/issues
Author-email: Nikolai Karetin <nicknaugam@gmail.com>
License-File: LICENSE
Classifier: License :: OSI Approved :: MIT License
Classifier: Operating System :: OS Independent
Classifier: Programming Language :: Python :: 3
Requires-Python: >=3.7
